{"openapi": "3.1.0", "info": {"title": "FastAPI", "version": "0.1.0"}, "paths": {"/process-video": {"post": {"summary": "Process Video", "description": "1. Save uploaded file locally.\n2. Detect scene boundaries.\n3. Extract audio.\n4. Run speaker diarization.\n5. Extract screenshots for each scene.\n6. Return scene info + diarization + screenshot paths.", "operationId": "process_video_process_video_post", "requestBody": {"content": {"multipart/form-data": {"schema": {"$ref": "#/components/schemas/Body_process_video_process_video_post"}}}, "required": true}, "responses": {"200": {"description": "Successful Response", "content": {"application/json": {"schema": {}}}}, "422": {"description": "Validation Error", "content": {"application/json": {"schema": {"$ref": "#/components/schemas/HTTPValidationError"}}}}}}}}, "components": {"schemas": {"Body_process_video_process_video_post": {"properties": {"file": {"type": "string", "format": "binary", "title": "File"}}, "type": "object", "required": ["file"], "title": "Body_process_video_process_video_post"}, "HTTPValidationError": {"properties": {"detail": {"items": {"$ref": "#/components/schemas/ValidationError"}, "type": "array", "title": "Detail"}}, "type": "object", "title": "HTTPValidationError"}, "ValidationError": {"properties": {"loc": {"items": {"anyOf": [{"type": "string"}, {"type": "integer"}]}, "type": "array", "title": "Location"}, "msg": {"type": "string", "title": "Message"}, "type": {"type": "string", "title": "Error Type"}}, "type": "object", "required": ["loc", "msg", "type"], "title": "ValidationError"}}}}